py_outrider/__init__.py
py_outrider/__main__.py
py_outrider/decoder_models.py
py_outrider/dispersion_models.py
py_outrider/distributions.py
py_outrider/hyperpar_opt.py
py_outrider/latent_space_models.py
py_outrider/main_run.py
py_outrider/models.py
py_outrider/outrider.py
py_outrider/parser.py
py_outrider/preprocess.py
py_outrider/utils/__init__.py
py_outrider/utils/float_limits.py
py_outrider/utils/io.py
py_outrider/utils/loss_list.py
py_outrider/utils/np_mom_theta.py
py_outrider/utils/print_func.py
py_outrider/utils/stats_func.py
py_outrider/utils/tf_fminbound.py
py_outrider/utils/tf_helper_func.py
py_outrider/utils/tf_init.py
utils/__init__.py
utils/float_limits.py
utils/io.py
utils/loss_list.py
utils/np_mom_theta.py
utils/print_func.py
utils/stats_func.py
utils/tf_fminbound.py
utils/tf_helper_func.py
utils/tf_init.py
py_outrider-0.1.0.dist-info/LICENSE
py_outrider-0.1.0.dist-info/METADATA
py_outrider-0.1.0.dist-info/WHEEL
py_outrider-0.1.0.dist-info/entry_points.txt
py_outrider-0.1.0.dist-info/top_level.txt
py_outrider-0.1.0.dist-info/RECORD
