Metadata-Version: 2.1
Name: py-outrider
Version: 0.1.0
Summary: Python backend package for OUTRIDER2 R package
Home-page: https://github.com/gagneurlab/py_outrider/
Author: Stefan Loipfinger, Ines Scheller
Author-email: scheller@in.tum.de
License: UNKNOWN
Platform: UNKNOWN
Classifier: Programming Language :: Python :: 3
Classifier: License :: OSI Approved :: MIT License
Classifier: Operating System :: OS Independent
Requires-Python: >=3.6
Requires-Dist: tensorflow (>=2.3.0)
Requires-Dist: tensorflow-probability (>=0.10.0)
Requires-Dist: scikit-learn (>=0.23.1)
Requires-Dist: statsmodels (>=0.11.1)
Requires-Dist: numpy (>=1.19.2)
Requires-Dist: pandas (>=1.1.5)
Requires-Dist: anndata (>=0.7.0)
Requires-Dist: nipals (>=0.5.2)
